odoo/addons/account_reconcile_model_strict_match_amount/README.rst
odoo/addons/account_reconcile_model_strict_match_amount/__init__.py
odoo/addons/account_reconcile_model_strict_match_amount/__manifest__.py
odoo/addons/account_reconcile_model_strict_match_amount/i18n/account_reconcile_model_strict_match_amount.pot
odoo/addons/account_reconcile_model_strict_match_amount/i18n/es.po
odoo/addons/account_reconcile_model_strict_match_amount/i18n/sv.po
odoo/addons/account_reconcile_model_strict_match_amount/models/__init__.py
odoo/addons/account_reconcile_model_strict_match_amount/models/account_reconcile_model.py
odoo/addons/account_reconcile_model_strict_match_amount/readme/CONTRIBUTORS.rst
odoo/addons/account_reconcile_model_strict_match_amount/readme/CREDITS.rst
odoo/addons/account_reconcile_model_strict_match_amount/readme/DESCRIPTION.rst
odoo/addons/account_reconcile_model_strict_match_amount/static/description/icon.png
odoo/addons/account_reconcile_model_strict_match_amount/static/description/index.html
odoo/addons/account_reconcile_model_strict_match_amount/tests/__init__.py
odoo/addons/account_reconcile_model_strict_match_amount/tests/test_account_reconcile_model_strict_match_amount.py
odoo/addons/account_reconcile_model_strict_match_amount/views/account_reconcile_model.xml
odoo14_addon_account_reconcile_model_strict_match_amount-14.0.1.0.1.dev10.dist-info/METADATA
odoo14_addon_account_reconcile_model_strict_match_amount-14.0.1.0.1.dev10.dist-info/WHEEL
odoo14_addon_account_reconcile_model_strict_match_amount-14.0.1.0.1.dev10.dist-info/top_level.txt
odoo14_addon_account_reconcile_model_strict_match_amount-14.0.1.0.1.dev10.dist-info/RECORD
